funrun/__init__.py
funrun/decorators.py
funrun/engine.py
funrun/product.py
funrun/rules.py
funrun/runner.py
funrun/shell/__init__.py
funrun/stdlib/__init__.py
funrun/stdlib/shell.py
funrun/utilities.py
funrun-0.1.0.dist-info/LICENSE
funrun-0.1.0.dist-info/METADATA
funrun-0.1.0.dist-info/WHEEL
funrun-0.1.0.dist-info/RECORD
