Metadata-Version: 2.1
Name: funrun
Version: 0.1.0
Summary: funrun
License: BSD-3
Author: Chris Mungall
Author-email: cjmungall@lbl.gov
Requires-Python: >=3.9,<4.0
Classifier: License :: Other/Proprietary License
Classifier: Programming Language :: Python :: 3
Classifier: Programming Language :: Python :: 3.9
Classifier: Programming Language :: Python :: 3.10
Classifier: Programming Language :: Python :: 3.11
Provides-Extra: docs
Provides-Extra: tests
Requires-Dist: click
Requires-Dist: importlib-metadata (>=4.8.0,<5.0.0)
